LICENSE
MANIFEST.in
README.rst
pyproject.toml
setup.py
CTid_programmer.egg-info/PKG-INFO
CTid_programmer.egg-info/SOURCES.txt
CTid_programmer.egg-info/dependency_links.txt
CTid_programmer.egg-info/entry_points.txt
CTid_programmer.egg-info/requires.txt
CTid_programmer.egg-info/top_level.txt
ctid_programmer/__init__.py
ctid_programmer/preferences.py
ctid_programmer/programmer.py
ctid_programmer/sensor_params.py
ctid_programmer/sn.py
ctid_programmer/sn_egauge.py
ctid_programmer/sn_local.py
ctid_programmer/template.py
ctid_programmer/gui/__init__.py
ctid_programmer/gui/main_window.py
ctid_programmer/gui/main_window_rc.py
ctid_programmer/gui/param_ct.py
ctid_programmer/gui/param_linear.py
ctid_programmer/gui/param_ntc.py
ctid_programmer/gui/param_pulse.py
ctid_programmer/gui/param_temp.py
ctid_programmer/gui/preferences_dialog.py
ctid_programmer/gui/template_dialog.py
ctid_programmer/resources/code/ac.hex
ctid_programmer/resources/code/powered.hex
share/applications/net.egauge.ctid_programmer.desktop
share/icons/net.egauge.ctid_programmer.svg